jsonpolars/__init__.py
jsonpolars/_version.py
jsonpolars/api.py
jsonpolars/arg.py
jsonpolars/base_dfop.py
jsonpolars/base_expr.py
jsonpolars/chain.py
jsonpolars/exc.py
jsonpolars/jskit.py
jsonpolars/model.py
jsonpolars/paths.py
jsonpolars/sentinel.py
jsonpolars/typehint.py
jsonpolars/utils_dfop.py
jsonpolars/utils_expr.py
jsonpolars/dfop/__init__.py
jsonpolars/dfop/aggregation.py
jsonpolars/dfop/api.py
jsonpolars/dfop/manipulation.py
jsonpolars/docs/__init__.py
jsonpolars/expr/__init__.py
jsonpolars/expr/api.py
jsonpolars/expr/column.py
jsonpolars/expr/dt.py
jsonpolars/expr/function.py
jsonpolars/expr/list.py
jsonpolars/expr/manipulation.py
jsonpolars/expr/operator.py
jsonpolars/expr/string.py
jsonpolars/expr/struct.py
jsonpolars/gen_code/__init__.py
jsonpolars/gen_code/dfop_api.jinja
jsonpolars/gen_code/expr_api.jinja
jsonpolars/gen_code/gen_api.py
jsonpolars/gen_code/supported_polars_expressions.jinja
jsonpolars/tests/__init__.py
jsonpolars/tests/dfop_case.py
jsonpolars/tests/expr_case.py
jsonpolars/tests/helper.py
jsonpolars/vendor/__init__.py
jsonpolars/vendor/better_dataclasses.py
jsonpolars/vendor/pytest_cov_helper.py
jsonpolars-0.4.2.dist-info/AUTHORS.rst
jsonpolars-0.4.2.dist-info/LICENSE.txt
jsonpolars-0.4.2.dist-info/METADATA
jsonpolars-0.4.2.dist-info/WHEEL
jsonpolars-0.4.2.dist-info/top_level.txt
jsonpolars-0.4.2.dist-info/RECORD
